{
    "engrave": {
        "보검": "images/enchant/enchant_sword.png",
        "지팡이": "images/enchant/enchant_staff.png",
        "성배": "images/enchant/enchant_grail.png",
        "별의 코인": "images/enchant/enchant_star.png"
    },
    "combination": {
        "보검+보검": "[풀HP] 상태의 적군을 액티브 공격 시, 크리티컬 확률이 20% 증가한다.",
        "지팡이+지팡이": "[일반 공격], 스킬 사용, 반격 및 지원 공격 후 임의 [2레벨 능력치 버프]를 1개 획득한다.",
        "별의 코인+별의 코인": "[부상] 상태일 경우, 대미지가 5% 증가하고 받는 대미지가 5% 감소한다. [빈사] 상태일 경우, 대미지가 10% 추가 증가하고 받는 대미지가 10% 추가 감소한다.",
        "성배+성배": "치료 효과가 10% 증가하고 받는 치료 효과가 10% 증가한다.",
        "보검+지팡이": "액티브 공격 전에 1칸 이동할 때마다 공격/방어 능력치가 4% 증가하며 최대 12% 증가한다. 해당 스킬은 다음 행동 시작 시까지 지속된다.",
        "지팡이+보검": "액티브 공격 전에 1칸 이동할 때마다 공격/방어 능력치가 4% 증가하며 최대 12% 증가한다. 해당 스킬은 다음 행동 시작 시까지 지속된다.",
        "보검+별의 코인": "[풀HP] 상태일 경우, 공격/방어 능력치가 12% 증가한다.",
        "별의 코인+보검": "[풀HP] 상태일 경우, 공격/방어 능력치가 12% 증가한다.",
        "보검+성배": "액티브 공격 전, 대미지가 5% 증가하고 15%의 [HP 흡수]를 발생시킨다.",
        "성배+보검": "액티브 공격 전, 대미지가 5% 증가하고 15%의 [HP 흡수]를 발생시킨다.",
        "지팡이+별의 코인": "받는 물리 대미지가 15% 감소한다.",
        "별의 코인+지팡이": "받는 물리 대미지가 15% 감소한다.",
        "지팡이+성배": "행동 종료시, 50% 확률로 [공명 각인]을 얻는다. 효과: 다음에 [액티브 스킬] 사용 시 소모한 에너지를 모두 반환하고 쿨타임이 초기화된다. (효과 쿨타임 4턴) (실시간 전투는 발동하지 않고, 효과는 HP, 공격/방어 능력치가 5% 증가하는 것으로 변경된다)",
        "성배+지팡이": "행동 종료시, 50% 확률로 [공명 각인]을 얻는다. 효과: 다음에 [액티브 스킬] 사용 시 소모한 에너지를 모두 반환하고 쿨타임이 초기화된다. (효과 쿨타임 4턴) (실시간 전투는 발동하지 않고, 효과는 HP, 공격/방어 능력치가 5% 증가하는 것으로 변경된다)",
        "별의 코인+성배": "받는 마법 대미지가 15% 감소한다.",
        "성배+별의 코인": "받는 마법 대미지가 15% 감소한다."
    }
}