{
    "name": "타이던",
    "class": "수호자",
    "stats": [
        {
            "name": "체력",
            "lv1": 412,
            "lv60": 3660
        },
        {
            "name": "물리 공격",
            "lv1": 201,
            "lv60": 1330
        },
        {
            "name": "마법 공격",
            "lv1": 141,
            "lv60": 933
        },
        {
            "name": "물리 방어",
            "lv1": 103,
            "lv60": 681
        },
        {
            "name": "마법 방어",
            "lv1": 44,
            "lv60": 295
        },
        {
            "name": "속도",
            "lv1": 235,
            "lv60": 235
        },
        {
            "name": "이동력",
            "lv1": 3,
            "lv60": 3
        }
    ],
    "build": [
        {
            "name": "기본 세팅",
            "skills": ["강력한 일격 (검)", "대형 방패", "위협", "견고한 방패", "대열 지휘"],
            "equipment": ["수호의 결의", "거대 결정석 방패", "절제된 욕망"],
            "comment": "버퍼형으로, 평타는 사용하지 않는다."
        },
        {
            "name": "엄벌의 방패 채용 시 세팅",
            "skills": ["강력한 일격 (검)", "대형 방패", "엄벌의 방패", "견고한 방패", "대열 지휘"],
            "equipment": ["수호의 결의", "거대 결정석 방패", "절제된 욕망"],
            "comment": "엄벌의 방패 채용 시"
        }
    ],
    "trait": {
        "name": "백전 방패",
        "image": "images/skill/taidon/taidon_passive.png",
        "star1": "[막기]를 보유한다. 행동 종료 시 타깃 방향 가로 3칸을 [경계]한다. 적이 해당 구역에 진입할 경우 60%의 [물리 범위 대미지]를 입힌다. 기타 [경계] 스킬을 직접 사용 시 공격력은 추가로 20% 증가한다.",
        "star2": "[막기]를 보유한다. 행동 종료 시 타깃 방향 가로 3칸을 [경계]한다. 적이 해당 구역에 진입할 경우 70%의 [물리 범위 대미지]를 입힌다. 기타 [경계] 스킬을 직접 사용 시 공격력은 추가로 20% 증가한다.",
        "star3": "[막기]를 보유한다. 행동 종료 시 타깃 방향 가로 3칸을 [경계]한다. 적이 해당 구역에 진입할 경우 80%의 [물리 범위 대미지]를 입힌다. 기타 [경계] 스킬을 직접 사용 시 공격력은 추가로 30% 증가한다.",
        "star4": "[막기]를 보유한다. 행동 종료 시 타깃 방향 가로 3칸을 [경계]한다. 적이 해당 구역에 진입할 경우 90%의 [물리 범위 대미지]를 입힌다. 기타 [경계] 스킬을 직접 사용 시 공격력은 추가로 30% 증가한다.",
        "star5": "[막기]를 보유한다. 행동 종료 시 타깃 방향 가로 3칸을 [경계]한다. 적이 해당 구역에 진입할 경우 100%의 [물리 범위 대미지]를 입힌다. 기타 [경계] 스킬을 직접 사용 시 공격력은 추가로 40% 증가한다."
    },
    "skills": {
        "RK0L": {
            "name": "슬래시"
        },
        "RK0R": {
            "name": "방어 태세"
        },
        "RK1L": {
            "name": "위협",
            "recommend": "recommend"
        },
        "RK1R": {
            "name": "기절 강타"
        },
        "RK3L": {
            "name": "사나운 타격"
        },
        "RK3R": {
            "name": "교란 전술",
            "recommend": "recommend"
        },
        "RK5L": {
            "name": "대형 방패",
            "recommend": "recommend"
        },
        "RK5R": {
            "name": "맞공격"
        },
        "RK7L": {
            "name": "대열 지휘",
            "recommend": "recommend"
        },
        "RK7R": {
            "name": "엄벌의 방패",
            "recommend": "optional"
        },
        "RK9L": {
            "name": "강력한 일격 (검)",
            "recommend": "recommend"
        },
        "RK9R": {
            "name": "한빙격 (검)"
        },
        "RK11L": {
            "name": "견고한 방패",
            "recommend": "recommend"
        },
        "RK11R": {
            "name": "생존 의지"
        }
    },
    
    "images": {
        "largePhoto": "images/awakening/taidon-awakening.png",
        "smallPhotos": [
            "기사 동맹",
            "철벽의 산"
        ]
    },
    "equipment": [
        {
            "name": "수호의 결의"
        },
        {
            "name": "거대 결정석 방패"
        },
        {
            "name": "절제된 욕망"
        },
        {
            "name": "불타는 칼날"
        },
        {
            "name": "거대 결정석 방패"
        },
        {
            "name": "은둔자의 고요"
        }
    ],
    "engrave": [
        {
            "name": "지팡이"
        },
        {
            "name": "별의 코인"
        },
        {
            "name": "별의 코인"
        },
        {
            "name": "별의 코인"
        }
    ]
}